tests/__init__.py
tests/test_builder.py
tests/test_parser.py
treef/__init__.py
treef/builder.py
treef/cli.py
treef/exceptions.py
treef/logger.py
treef/parser.py
treef-0.1.0.dist-info/licenses/LICENSE
treef-0.1.0.dist-info/METADATA
treef-0.1.0.dist-info/WHEEL
treef-0.1.0.dist-info/entry_points.txt
treef-0.1.0.dist-info/top_level.txt
treef-0.1.0.dist-info/RECORD
