Metadata-Version: 2.4
Name: treef
Version: 0.1.0
Summary: A tool to create project structures from .tree files.
License: Apache-2.0
Requires-Python: >=3.8
License-File: LICENSE
Requires-Dist: click>=8.0
Dynamic: license-file
